MANIFEST.in
README.md
setup.py
QDMTK.egg-info/PKG-INFO
QDMTK.egg-info/SOURCES.txt
QDMTK.egg-info/dependency_links.txt
QDMTK.egg-info/requires.txt
QDMTK.egg-info/top_level.txt
qdmtk/__init__.py
qdmtk/exceptions.py
qdmtk/icon.svg
qdmtk/icon_dj.svg
qdmtk/icon_pg.svg
qdmtk/metadata.txt
qdmtk/plugin.py
qdmtk/provider.py
qdmtk/requirements.txt
qdmtk/router.py
qdmtk/utils.py
qdmtk/version.py