Metadata-Version: 2.1
Name: QDMTK
Version: 0.0.2a1
Summary: QGIS Datamodel toolkit
Home-page: https://github.com/opengisch/qdmtk
Author: Olivier Dalang
Author-email: olivier@opengis.ch
License: UNKNOWN
Platform: UNKNOWN
